LICENSE
MANIFEST.in
README.md
setup.cfg
setup.py
requirements/requirements.txt
src/os_scrapy_cookiecutter/VERSION
src/os_scrapy_cookiecutter/__init__.py
src/os_scrapy_cookiecutter.egg-info/PKG-INFO
src/os_scrapy_cookiecutter.egg-info/SOURCES.txt
src/os_scrapy_cookiecutter.egg-info/dependency_links.txt
src/os_scrapy_cookiecutter.egg-info/not-zip-safe
src/os_scrapy_cookiecutter.egg-info/requires.txt
src/os_scrapy_cookiecutter.egg-info/top_level.txt
src/os_scrapy_cookiecutter/templates/cookiecutter.json
src/os_scrapy_cookiecutter/templates/hooks/post_gen_project.py
src/os_scrapy_cookiecutter/templates/hooks/pre_gen_project.py
src/os_scrapy_cookiecutter/templates/{{cookiecutter.project_dir}}/.coveragerc
src/os_scrapy_cookiecutter/templates/{{cookiecutter.project_dir}}/.gitignore
src/os_scrapy_cookiecutter/templates/{{cookiecutter.project_dir}}/LICENSE
src/os_scrapy_cookiecutter/templates/{{cookiecutter.project_dir}}/MANIFEST.in
src/os_scrapy_cookiecutter/templates/{{cookiecutter.project_dir}}/README.md
src/os_scrapy_cookiecutter/templates/{{cookiecutter.project_dir}}/pytest.ini
src/os_scrapy_cookiecutter/templates/{{cookiecutter.project_dir}}/setup.cfg
src/os_scrapy_cookiecutter/templates/{{cookiecutter.project_dir}}/setup.py
src/os_scrapy_cookiecutter/templates/{{cookiecutter.project_dir}}/tox.ini
src/os_scrapy_cookiecutter/templates/{{cookiecutter.project_dir}}/requirements/requirements-lint.txt
src/os_scrapy_cookiecutter/templates/{{cookiecutter.project_dir}}/requirements/requirements-test.txt
src/os_scrapy_cookiecutter/templates/{{cookiecutter.project_dir}}/requirements/requirements.txt
src/os_scrapy_cookiecutter/templates/{{cookiecutter.project_dir}}/scripts/lint.sh
src/os_scrapy_cookiecutter/templates/{{cookiecutter.project_dir}}/scripts/test.sh
src/os_scrapy_cookiecutter/templates/{{cookiecutter.project_dir}}/tests/__init__.py
src/os_scrapy_cookiecutter/templates/{{cookiecutter.project_dir}}/tests/test_scrapy_check.py
tests/__init__.py
tests/test_version.py