Metadata-Version: 2.1
Name: os-scrapy-cookiecutter
Version: 0.0.9
Summary: Cookiecutter for Scrapy
Home-page: https://github.com/cfhamlet/os-scrapy-cookiecutter
Author: Ozzy
Author-email: cfhamlet@gmail.com
License: MIT License
Keywords: cookiecutter,template,package
Platform: UNKNOWN
Classifier: Development Status :: 2 - Pre-Alpha
Classifier: Intended Audience :: Developers
Classifier: License :: OSI Approved :: MIT License
Classifier: Natural Language :: English
Classifier: Programming Language :: Python :: 3
Classifier: Programming Language :: Python :: 3.6
Classifier: Programming Language :: Python :: 3 :: Only
Classifier: Programming Language :: Python :: Implementation :: CPython
Classifier: Programming Language :: Python :: Implementation :: PyPy
Requires-Python: >=3.6
